qattools/__init__.py
qattools/describe.py
qattools/imex.py
qattools/to.py
qattools/what.py
qattools-0.5.1.dist-info/WHEEL
qattools-0.5.1.dist-info/METADATA
qattools-0.5.1.dist-info/RECORD
