Metadata-Version: 2.1
Name: qattools
Version: 0.5.1
Summary: 
Author: Richard Hajek
Author-email: richard.m.hajek@gmail.com
Requires-Python: >=3.7,<4.0
Classifier: Programming Language :: Python :: 3
Classifier: Programming Language :: Python :: 3.7
Classifier: Programming Language :: Python :: 3.8
Classifier: Programming Language :: Python :: 3.9
Classifier: Programming Language :: Python :: 3.10
Classifier: Programming Language :: Python :: 3.11
Requires-Dist: pandas
Requires-Dist: torch
Requires-Dist: torchinfo
